RPBook/RPbook.py
RPBook/__init__.py
RPBook/assets/RPbook/RPbook.js
RPBook/assets/RPbook/RPbook.min.js
RPBook/assets/RPbook/RPbook.min.js.map
RPBook/assets/RPbook/jquery-3.3.1.min.js
RPBook/assets/RPbook/jquery.mark.js
RPBook/assets/RPbook/images/apple-touch-icon-precomposed-152.png
RPBook/assets/RPbook/images/favicon.ico
RPBook/assets/RPbook/jquery_mar/jquery.mark.es6.js
RPBook/assets/RPbook/jquery_mar/jquery.mark.es6.min.js
RPBook/assets/RPbook/jquery_mar/jquery.mark.js
RPBook/assets/RPbook/jquery_mar/jquery.mark.min.js
RPBook/assets/RPbook/jquery_mar/mark.es6.js
RPBook/assets/RPbook/jquery_mar/mark.es6.min.js
RPBook/assets/RPbook/jquery_mar/mark.js
RPBook/assets/RPbook/jquery_mar/mark.min.js
RPBook/assets/RPbook/katex/README.md
RPBook/assets/RPbook/katex/katex.css
RPBook/assets/RPbook/katex/katex.js
RPBook/assets/RPbook/katex/katex.min.css
RPBook/assets/RPbook/katex/katex.min.js
RPBook/assets/RPbook/katex/katex.mjs
RPBook/assets/RPbook/katex/contrib/auto-render.js
RPBook/assets/RPbook/katex/contrib/auto-render.min.js
RPBook/assets/RPbook/katex/contrib/auto-render.mjs
RPBook/assets/RPbook/katex/contrib/copy-tex.css
RPBook/assets/RPbook/katex/contrib/copy-tex.js
RPBook/assets/RPbook/katex/contrib/copy-tex.min.css
RPBook/assets/RPbook/katex/contrib/copy-tex.min.js
RPBook/assets/RPbook/katex/contrib/copy-tex.mjs
RPBook/assets/RPbook/katex/contrib/mathtex-script-type.js
RPBook/assets/RPbook/katex/contrib/mathtex-script-type.min.js
RPBook/assets/RPbook/katex/contrib/mathtex-script-type.mjs
RPBook/assets/RPbook/katex/contrib/mhchem.js
RPBook/assets/RPbook/katex/contrib/mhchem.min.js
RPBook/assets/RPbook/katex/contrib/mhchem.mjs
RPBook/assets/RPbook/katex/fonts/KaTeX_AMS-Regular.ttf
RPBook/assets/RPbook/katex/fonts/KaTeX_AMS-Regular.woff
RPBook/assets/RPbook/katex/fonts/KaTeX_AMS-Regular.woff2
RPBook/assets/RPbook/katex/fonts/KaTeX_Caligraphic-Bold.ttf
RPBook/assets/RPbook/katex/fonts/KaTeX_Caligraphic-Bold.woff
RPBook-1.0.19.dist-info/LICENSE
RPBook-1.0.19.dist-info/METADATA
RPBook-1.0.19.dist-info/WHEEL
RPBook-1.0.19.dist-info/entry_points.txt
RPBook-1.0.19.dist-info/top_level.txt
RPBook-1.0.19.dist-info/zip-safe
RPBook-1.0.19.dist-info/RECORD
