Metadata-Version: 2.1
Name: RPBook
Version: 1.0.19
Summary: markdown 静态网页生成器
Home-page: https://github.com/Andyemmmm/RPBook
Author: 曾润平
Author-email: 1450644462@qq.com
License: MIT
Project-URL: 样板, https://andyemmmm.github.io/
Keywords: RPbook md
Platform: UNKNOWN
Classifier: Development Status :: 5 - Production/Stable
Classifier: Intended Audience :: Developers
Classifier: License :: OSI Approved :: MIT License
Classifier: Natural Language :: Chinese (Simplified)
Classifier: Programming Language :: Python
Classifier: Programming Language :: Python :: 3.7
Classifier: Programming Language :: Python :: Implementation :: CPython
Classifier: Programming Language :: Python :: Implementation :: PyPy
Requires-Dist: mistletoe
